TOPSIS_Shivam_101853021/__init__.py
TOPSIS_Shivam_101853021/topsis.py
TOPSIS_Shivam_101853021-0.1.dist-info/LICENSE
TOPSIS_Shivam_101853021-0.1.dist-info/METADATA
TOPSIS_Shivam_101853021-0.1.dist-info/WHEEL
TOPSIS_Shivam_101853021-0.1.dist-info/top_level.txt
TOPSIS_Shivam_101853021-0.1.dist-info/RECORD
