Metadata-Version: 2.1
Name: TOPSIS-Shivam-101853021
Version: 0.1
Summary: A Project based on TOPSIS
Home-page: https://github.com/neoteroi/essentials-openapi
Author: ShivamRajSingh
Author-email: shivamrajsingh3009@gmail.com
License: MIT
Keywords: core package
Platform: UNKNOWN
Classifier: Development Status :: 4 - Beta
Classifier: License :: OSI Approved :: MIT License
Classifier: Programming Language :: Python :: 3
Classifier: Programming Language :: Python :: 3.6
Classifier: Programming Language :: Python :: 3.7
Classifier: Programming Language :: Python :: 3.8
Classifier: Programming Language :: Python :: 3.9
Classifier: Operating System :: OS Independent
Requires-Dist: Pandas
